[
  {
    "id": "fake_snare_bait",
    "type": "TOOL",
    "category": "other",
    "name": { "str": "fake snare tracker" },
    "description": "This is a fake item used to track snare status. If you have this, it's a bug.",
    "weight": "1 g",
    "volume": "1 ml",
    "price": 0,
    "price_postapoc": 0,
    "material": [ "wood" ],
    "symbol": "*",
    "color": "white",
    "flags": [ "TRADER_AVOID", "FAKE_SNARE" ]
  },
  {
    "id": "rattrap",
    "type": "TOOL",
    "category": "deployables",
    "name": { "str": "rat trap" },
    "description": "A small spring-loaded trap designed to catch rats. Activate it to set it up.",
    "weight": "200 g",
    "volume": "500 ml",
    "price": 500,
    "price_postapoc": 100,
    "material": [ "iron", "wood" ],
    "symbol": "^",
    "color": "brown",
    "use_action": { "type": "deploy_furn", "furn_type": "f_rattrap_empty" }
  },
  {
    "id": "large_rattrap",
    "type": "TOOL",
    "category": "deployables",
    "name": { "str": "large rat trap" },
    "description": "A large spring-loaded trap designed to catch bigger rodents. Activate it to set it up.",
    "weight": "500 g",
    "volume": "1500 ml",
    "price": 1200,
    "price_postapoc": 300,
    "material": [ "iron", "wood" ],
    "symbol": "^",
    "color": "dark_brown",
    "use_action": { "type": "deploy_furn", "furn_type": "f_big_rattrap_empty" }
  },
  {
    "id": "beartrap_hunting",
    "type": "TOOL",
    "category": "deployables",
    "name": { "str": "hunting bear trap" },
    "description": "A large spring-loaded pair of jaws connected to a sensitive pressure plate. This is altered from a standard bear trap to be more effective for hunting. Activate it to set it up.",
    "copy-from": "beartrap",
    "material": [ "steel" ],
    "symbol": "^",
    "color": "dark_gray",
    "use_action": { "type": "deploy_furn", "furn_type": "f_beartrap_empty" }
  },
  {
    "id": "test_bait",
    "type": "COMESTIBLE",
    "comestible_type": "FOOD",
    "name": { "str": "test bait" },
    "description": "Testing bait for hunting snares.",
    "weight": "10 g",
    "volume": "10 ml",
    "price": 100,
    "material": [ "flesh" ],
    "symbol": "%",
    "color": "brown",
    "spoils_in": "3 days",
    "flags": [ "INEDIBLE", "BAIT_SMALL_GAME_HERBIVORE" ],
    "calories": 50,
    "fun": -5
  }
]
